pyZuoraEncode/__init__.py
pyZuoraEncode/functions.py
pyZuoraEncodeV2-1.1.dist-info/LICENSE
pyZuoraEncodeV2-1.1.dist-info/METADATA
pyZuoraEncodeV2-1.1.dist-info/WHEEL
pyZuoraEncodeV2-1.1.dist-info/top_level.txt
pyZuoraEncodeV2-1.1.dist-info/RECORD
